reliability/ALT_fitters.py
reliability/Convert_data.py
reliability/Datasets.py
reliability/Distributions.py
reliability/Fitters.py
reliability/Nonparametric.py
reliability/Other_functions.py
reliability/PoF.py
reliability/Probability_plotting.py
reliability/Reliability_testing.py
reliability/Repairable_systems.py
reliability/Utils.py
reliability/__init__.py
reliability-0.9.0.dist-info/LICENSE
reliability-0.9.0.dist-info/METADATA
reliability-0.9.0.dist-info/WHEEL
reliability-0.9.0.dist-info/top_level.txt
reliability-0.9.0.dist-info/RECORD
