Metadata-Version: 2.2
Name: reliability
Version: 0.9.0
Summary: Reliability Engineering toolkit for Python
Home-page: https://reliability.readthedocs.io/en/latest/
Author: Matthew Reid
Author-email: alpha.reliability@gmail.com
License: LGPLv3
Project-URL: Documentation, https://reliability.readthedocs.io/en/latest/
Project-URL: Source Code, https://github.com/MatthewReid854/reliability
Project-URL: Donate, https://reliability.readthedocs.io/en/latest/How%20to%20donate%20to%20the%20project.html
Keywords: reliability,engineering,RAM,weibull,lognormal,exponential,beta,gamma,normal,loglogistic,gumbel,extreme,value,kaplan meier,kaplan-meier,survival,analysis,censored,data,lifelines,probability,distribution,distributions,fit,fitting,curve,quality,ALT,accelerated,life,testing,MCF,mean,cumulative,CIF,DS,ZI,defective,subpopulation,zero,inflated,DSZI,likelihood
Classifier: Intended Audience :: Science/Research
Classifier: Topic :: Scientific/Engineering
Classifier: Programming Language :: Python :: 3
Classifier: Development Status :: 5 - Production/Stable
Classifier: License :: OSI Approved :: GNU Lesser General Public License v3 (LGPLv3)
Requires-Python: >=3.10
License-File: LICENSE
Requires-Dist: autograd>=1.7.0
Requires-Dist: scipy>=1.15.0
Requires-Dist: numpy>=2.2.0
Requires-Dist: matplotlib>=3.10.0
Requires-Dist: pandas>=2.2.0
Requires-Dist: autograd-gamma>=0.5.0
Requires-Dist: mplcursors>=0.6
Dynamic: author
Dynamic: author-email
Dynamic: classifier
Dynamic: description
Dynamic: description-content-type
Dynamic: home-page
Dynamic: keywords
Dynamic: license
Dynamic: project-url
Dynamic: requires-dist
Dynamic: requires-python
Dynamic: summary
